{
  "RawText": "M A H N O O R\n0301-0806404\nM u z a f f a r\nmahnoormuzaffar03@gmail.com\nS O F T W A R E E N G I N E E R\nHouse # 3436 Mehmodabad # 2 KDA\nTP2 Karachi I Highly driven software developer with growing knowledge in data\ndynamics and Software development SDLC and STLC testing lifecycle\nwith the new technologies such as Python,C#,ASP .NET,JAVA for\nS K I L L S\napplication development and HTML ,CSSS,JAVASCRIPT for web\ndevelopment .I am ready to contribute my skills and passion to help\nASP .NET C#\ndrive innovation as a successful software developer\nASP .NET MVC\nASP .NET Web forms\nE X P E R I E N C E\nDesign Patterns\nSQL server\nINTERN\nData Structures\nJILANSOFT (Software House)\nJuly 2024- Sep 2024\nOOP Concepts\nAccomplished increase in patient record reliability and a 50% boost in visit\njQuery\nfrequency and billing efficiency by developing a secure, full-stack hospital\nBootstrap\nmanagement system using ASP.NET and MS SQL Server by implementing\nHTML, CSS\nresponsive UI with Bootstrap and JavaScript, and designing robust\nJavaScript\nmodules for patient records, billing, and refunds using C#, HTML, and CSS.\nPython\nINTERN\nGitHub\nNAVAL SOFTWARE DEPARTMENT\nRequirement Analysis\nAug 2024 - Oct 2024\n\u0060\nStrong Communication\nAccomplished a 40% improvement in logistics data accuracy and a 35%\nreduction in processing time by developing a robust logistics management\napplication using Java and MySQL by designing an optimized database\nE D U C A T I O N\nschema and implementing secure, efficient backend data processing,\nSOFTWARE ENGINEERING BSE\nstrengthening backend development and database management skills.\nBAHRIA UNIVERSITY KARACHI\nP R O J E C T S\n2022 - Present\nPROPSOFT WEBSITE (RENTAL MANAGEMENT SYSTEM)\nHTML, CSS, JavaScript, ASP.NET C#, and SQL Server\nParticipated in Tech competitions\nHOSPITAL MANAGEMENT SYSTEM\nMember of community support\nHTML, CSS, JavaScript, ASP.NET C#, and SQL Server\nprogram\nGeneral Secretary of Bahria University PERSONALITY ANALYSER FROM LINKEDIN AND GITHUB\nPython ,Web Scrapping for Github data\nDevelopers Society\nCGPA : 3.62\nFOOD DONATION AND PICKUP PLATFORM\nMERN Stack\nAIRLINE MANAGEMENT SYSTM\nL A N G U A G E\nC# AND DATABSE AS SQL\nHOTEL MANAGEMENT SYSTM\nEnglish\nJAVA AND DATABASE AS MYSQL \u002B OOP Concepts\nUrdu\nTRAVERSAL TREK (DATA STRUCTURES)\nJAVA AND NO DATABSE\nTRAVEL AND TOURISM MANAGEMENT SYSTM\nJAVA AND DATABSE AS MYSQL\nPIZZA ORDERING WEBSITE PIZZA-LICIOUS\nHTML CSS JAVASCRIPT ,MS ACCESS",
  "Emails": [
    "mahnoormuzaffar03@gmail.com"
  ],
  "Phones": [
    "0301-0806404"
  ],
  "Name": "Mahnoormuzaffar03",
  "Skills": [
    "ASP .NET C#",
    "ASP .NET MVC",
    "ASP .NET Web forms",
    "E X P E R I E N C E",
    "Design Patterns",
    "SQL server",
    "Data Structures",
    "JILANSOFT (Software House)",
    "OOP Concepts",
    "Accomplished increase in patient record reliability and a 50% boost in visit",
    "jQuery",
    "frequency and billing efficiency by developing a secure",
    "full",
    "stack hospital",
    "Bootstrap",
    "management system using ASP.NET and MS SQL Server by implementing",
    "HTML",
    "CSS",
    "responsive UI with Bootstrap and JavaScript",
    "and designing robust",
    "JavaScript",
    "modules for patient records",
    "billing",
    "and refunds using C#",
    "HTML",
    "and CSS.",
    "Python",
    "GitHub",
    "NAVAL SOFTWARE DEPARTMENT",
    "Requirement Analysis",
    "Strong Communication",
    "Accomplished a 40% improvement in logistics data accuracy and a 35%",
    "reduction in processing time by developing a robust logistics management",
    "application using Java and MySQL by designing an optimized database",
    "E D U C A T I O N",
    "schema and implementing secure",
    "efficient backend data processing",
    "BAHRIA UNIVERSITY KARACHI",
    "P R O J E C T S",
    "PROPSOFT WEBSITE (RENTAL MANAGEMENT SYSTEM)",
    "HTML",
    "CSS",
    "JavaScript",
    "ASP.NET C#",
    "and SQL Server",
    "Participated in Tech competitions",
    "HOSPITAL MANAGEMENT SYSTEM",
    "Member of community support",
    "HTML",
    "CSS",
    "JavaScript",
    "ASP.NET C#",
    "and SQL Server",
    "program",
    "General Secretary of Bahria University PERSONALITY ANALYSER FROM LINKEDIN AND GITHUB",
    "Python",
    "Web Scrapping for Github data",
    "CGPA : 3.62",
    "FOOD DONATION AND PICKUP PLATFORM",
    "MERN Stack",
    "AIRLINE MANAGEMENT SYSTM",
    "L A N G U A G E",
    "C# AND DATABSE AS SQL",
    "HOTEL MANAGEMENT SYSTM",
    "English",
    "JAVA AND DATABASE AS MYSQL \u002B OOP Concepts",
    "Urdu",
    "TRAVERSAL TREK (DATA STRUCTURES)",
    "JAVA AND NO DATABSE",
    "TRAVEL AND TOURISM MANAGEMENT SYSTM",
    "JAVA AND DATABSE AS MYSQL",
    "PIZZA ORDERING WEBSITE PIZZA",
    "LICIOUS",
    "HTML CSS JAVASCRIPT",
    "MS ACCESS"
  ],
  "Experience": [],
  "Education": [],
  "Sections": {
    "top": [
      "M A H N O O R",
      "0301-0806404",
      "M u z a f f a r",
      "mahnoormuzaffar03@gmail.com",
      "S O F T W A R E E N G I N E E R",
      "House # 3436 Mehmodabad # 2 KDA",
      "TP2 Karachi I Highly driven software developer with growing knowledge in data",
      "dynamics and Software development SDLC and STLC testing lifecycle",
      "with the new technologies such as Python,C#,ASP .NET,JAVA for",
      "S K I L L S",
      "application development and HTML ,CSSS,JAVASCRIPT for web"
    ],
    "skills": [
      "ASP .NET C#",
      "drive innovation as a successful software developer",
      "ASP .NET MVC",
      "ASP .NET Web forms",
      "E X P E R I E N C E",
      "Design Patterns",
      "SQL server",
      "INTERN",
      "Data Structures",
      "JILANSOFT (Software House)",
      "July 2024- Sep 2024",
      "OOP Concepts",
      "Accomplished increase in patient record reliability and a 50% boost in visit",
      "jQuery",
      "frequency and billing efficiency by developing a secure, full-stack hospital",
      "Bootstrap",
      "management system using ASP.NET and MS SQL Server by implementing",
      "HTML, CSS",
      "responsive UI with Bootstrap and JavaScript, and designing robust",
      "JavaScript",
      "modules for patient records, billing, and refunds using C#, HTML, and CSS.",
      "Python",
      "INTERN",
      "GitHub",
      "NAVAL SOFTWARE DEPARTMENT",
      "Requirement Analysis",
      "Aug 2024 - Oct 2024",
      "\u0060",
      "Strong Communication",
      "Accomplished a 40% improvement in logistics data accuracy and a 35%",
      "reduction in processing time by developing a robust logistics management",
      "application using Java and MySQL by designing an optimized database",
      "E D U C A T I O N",
      "schema and implementing secure, efficient backend data processing,",
      "SOFTWARE ENGINEERING BSE",
      "BAHRIA UNIVERSITY KARACHI",
      "P R O J E C T S",
      "2022 - Present",
      "PROPSOFT WEBSITE (RENTAL MANAGEMENT SYSTEM)",
      "HTML, CSS, JavaScript, ASP.NET C#, and SQL Server",
      "Participated in Tech competitions",
      "HOSPITAL MANAGEMENT SYSTEM",
      "Member of community support",
      "HTML, CSS, JavaScript, ASP.NET C#, and SQL Server",
      "program",
      "General Secretary of Bahria University PERSONALITY ANALYSER FROM LINKEDIN AND GITHUB",
      "Python ,Web Scrapping for Github data",
      "Developers Society",
      "CGPA : 3.62",
      "FOOD DONATION AND PICKUP PLATFORM",
      "MERN Stack",
      "AIRLINE MANAGEMENT SYSTM",
      "L A N G U A G E",
      "C# AND DATABSE AS SQL",
      "HOTEL MANAGEMENT SYSTM",
      "English",
      "JAVA AND DATABASE AS MYSQL \u002B OOP Concepts",
      "Urdu",
      "TRAVERSAL TREK (DATA STRUCTURES)",
      "JAVA AND NO DATABSE",
      "TRAVEL AND TOURISM MANAGEMENT SYSTM",
      "JAVA AND DATABSE AS MYSQL",
      "PIZZA ORDERING WEBSITE PIZZA-LICIOUS",
      "HTML CSS JAVASCRIPT ,MS ACCESS"
    ]
  }
}